terraformpy/__init__.py
terraformpy/cli.py
terraformpy/helpers.py
terraformpy/objects.py
terraformpy/resource_collections.py
terraformpy/hooks/__init__.py
terraformpy/hooks/aws.py
terraformpy-1.3.5.dist-info/LICENSE
terraformpy-1.3.5.dist-info/METADATA
terraformpy-1.3.5.dist-info/WHEEL
terraformpy-1.3.5.dist-info/entry_points.txt
terraformpy-1.3.5.dist-info/top_level.txt
terraformpy-1.3.5.dist-info/RECORD
