Metadata-Version: 2.1
Name: terraformpy
Version: 1.3.5
Summary: Terraformpy is a library and command line tool to supercharge your Terraform configs using a full fledged Python environment!
Home-page: https://github.com/NerdWalletOSS/terraformpy
Author: Evan Borgstrom
Author-email: eborgstrom@nerdwallet.com
License: UNKNOWN
Platform: UNKNOWN
Classifier: Development Status :: 5 - Production/Stable
Classifier: Environment :: Console
Classifier: Intended Audience :: Developers
Classifier: Intended Audience :: Information Technology
Classifier: Intended Audience :: System Administrators
Classifier: License :: OSI Approved :: Apache Software License
Classifier: Natural Language :: English
Classifier: Programming Language :: Python
Classifier: Topic :: Software Development :: Libraries
Classifier: Topic :: Software Development :: Pre-processors
Classifier: Topic :: System :: Systems Administration
License-File: LICENSE
Requires-Dist: schematics (<3.0,>=2.0)
Requires-Dist: six (<2,>=1.11)
Provides-Extra: dev
Requires-Dist: pytest-mock ; extra == 'dev'
Requires-Dist: pytest-cov ; extra == 'dev'
Requires-Dist: codecov ; extra == 'dev'
Requires-Dist: pytest (<4.7,>=4.6) ; (python_version <= "2.7") and extra == 'dev'
Requires-Dist: pytest (<6,>=5.0) ; (python_version > "3") and extra == 'dev'
